liblivemedia/__init__.py
liblivemedia/liblivemedia.cp313-win_amd64.pyd
liblivemedia-1.0.5.dist-info/COPYING
liblivemedia-1.0.5.dist-info/COPYING.LESSER
liblivemedia-1.0.5.dist-info/METADATA
liblivemedia-1.0.5.dist-info/WHEEL
liblivemedia-1.0.5.dist-info/top_level.txt
liblivemedia-1.0.5.dist-info/RECORD
