Metadata-Version: 2.1
Name: liblivemedia
Version: 1.0.5
Summary: A python module based on live555, version 2024.06.26
Author: Stephen Rhodes
Author-email: Stephen Rhodes <sr99622@gmail.com>
Project-URL: Homepage, https://github.com/sr99622/liblivemedia
Project-URL: Bug Tracker, https://github.com/sr99622/liblivemedia/issues
Classifier: Programming Language :: Python :: 3
Classifier: License :: OSI Approved :: GNU Lesser General Public License v2 (LGPLv2)
Classifier: Operating System :: OS Independent
Requires-Python: >=3.10
License-File: COPYING
License-File: COPYING.LESSER
